[
  {
    "Merchant": "pishposhbaby",
    "End Date": "NEVER",
    "Title": "Mamas&amp;Papas Bundle - just $400!",
    "Tracking URL": "https://www.shareasale.com/u.cfm?d=580416&m=63814&u=233101",
    "Category": "car seats",
    "Description": "Mamas&amp;Papas Bundle - just $400!",
    "Coupon Code": ""
  },
  {
    "Merchant": "pishposhbaby",
    "End Date": "NEVER",
    "Title": "Save $40 on the Boon Flair ",
    "Tracking URL": "https://www.shareasale.com/u.cfm?d=580415&m=63814&u=233101",
    "Category": "car seats",
    "Description": "Save $40 on the Boon Flair ",
    "Coupon Code": ""
  },
  {
    "Merchant": "pishposhbaby",
    "End Date": "NEVER",
    "Title": "Save $200 on the Baby Monsters Easy Twin!",
    "Tracking URL": "https://www.shareasale.com/u.cfm?d=580414&m=63814&u=233101",
    "Category": "car seats",
    "Description": "Save $200 on the Baby Monsters Easy Twin!",
    "Coupon Code": ""
  },
  {
    "Merchant": "pishposhbaby",
    "End Date": "NEVER",
    "Title": "Save $200 on the 2018 Bugaboo Cameleon3!",
    "Tracking URL": "https://www.shareasale.com/u.cfm?d=580413&m=63814&u=233101",
    "Category": "car seats",
    "Description": "Save $200 on the 2018 Bugaboo Cameleon3!",
    "Coupon Code": ""
  },
  {
    "Merchant": "pishposhbaby",
    "End Date": "NEVER",
    "Title": "$300 off the Silver Cross Wave 2018!",
    "Tracking URL": "https://www.shareasale.com/u.cfm?d=580412&m=63814&u=233101",
    "Category": "car seats",
    "Description": "$300 off the Silver Cross Wave 2018!",
    "Coupon Code": ""
  },
  {
    "Merchant": "pishposhbaby",
    "End Date": "NEVER",
    "Title": "Save 20% on Vista Denny!",
    "Tracking URL": "https://www.shareasale.com/u.cfm?d=580411&m=63814&u=233101",
    "Category": "car seats",
    "Description": "Save 20% on Vista Denny!",
    "Coupon Code": ""
  },
  {
    "Merchant": "pishposhbaby",
    "End Date": "NEVER",
    "Title": "Save $20 on Nuna Pipa!",
    "Tracking URL": "https://www.shareasale.com/u.cfm?d=580410&m=63814&u=233101",
    "Category": "car seats",
    "Description": "Save $20 on Nuna Pipa!",
    "Coupon Code": ""
  },
  {
    "Merchant": "pishposhbaby",
    "End Date": "NEVER",
    "Title": "Save $150 on Nuna Mixx2!",
    "Tracking URL": "https://www.shareasale.com/u.cfm?d=580409&m=63814&u=233101",
    "Category": "car seats",
    "Description": "Save $150 on Nuna Mixx2!",
    "Coupon Code": ""
  },
  {
    "Merchant": "pishposhbaby",
    "End Date": "NEVER",
    "Title": "Save 30% on 2018 Baby Jogger strollers!",
    "Tracking URL": "https://www.shareasale.com/u.cfm?d=580408&m=63814&u=233101",
    "Category": "car seats",
    "Description": "Save 30% on 2018 Baby Jogger strollers!",
    "Coupon Code": ""
  },
  {
    "Merchant": "pishposhbaby",
    "End Date": "NEVER",
    "Title": "Save 10% o 2018 Clek Foonf and Fllo car seats",
    "Tracking URL": "https://www.shareasale.com/u.cfm?d=580407&m=63814&u=233101",
    "Category": "car seats",
    "Description": "Save 10% o 2018 Clek Foonf and Fllo car seats",
    "Coupon Code": ""
  }
]