[
  {
    "Merchant": "TideWe",
    "End Date": "NEVER",
    "Title": "18% OFF HUNTING GEAR",
    "Tracking URL": "https://www.shareasale.com/u.cfm?d=1272323&m=92895&u=233101",
    "Category": "deal",
    "Description": "SAVE 18% OFF NOW!",
    "Coupon Code": "DEAL18"
  },
  {
    "Merchant": "TideWe",
    "End Date": "NEVER",
    "Title": "30% OFF SEASON SALE",
    "Tracking URL": "https://www.shareasale.com/u.cfm?d=1034404&m=92895&u=233101",
    "Category": "Clearance item",
    "Description": "30% OFF SEASON SALE",
    "Coupon Code": "HSE22"
  },
  {
    "Merchant": "TideWe",
    "End Date": "NEVER",
    "Title": "Save More with Bundle!",
    "Tracking URL": "https://www.shareasale.com/u.cfm?d=1269135&m=92895&u=233101",
    "Category": "deal",
    "Description": "Save More with Bundle",
    "Coupon Code": ""
  },
  {
    "Merchant": "TideWe",
    "End Date": "NEVER",
    "Title": "Turkey Hunting Bundle Sales",
    "Tracking URL": "https://www.shareasale.com/u.cfm?d=1269134&m=92895&u=233101",
    "Category": "deal",
    "Description": "",
    "Coupon Code": ""
  },
  {
    "Merchant": "TideWe",
    "End Date": "NEVER",
    "Title": "Flash Sale for Hunting Gear",
    "Tracking URL": "https://www.shareasale.com/u.cfm?d=1114548&m=92895&u=233101",
    "Category": "Flash Sale",
    "Description": "FLASH SALE FROM EVERY TUESDAY TO FRIDAY",
    "Coupon Code": ""
  },
  {
    "Merchant": "TideWe",
    "End Date": "NEVER",
    "Title": "Hunting Gear Clearance - Buy 2, Get 2nd 50% OFF",
    "Tracking URL": "https://www.shareasale.com/u.cfm?d=1111606&m=92895&u=233101",
    "Category": "Clearance item",
    "Description": "Buy 2 Get 2nd 50% off clearance items",
    "Coupon Code": "TWS50"
  },
  {
    "Merchant": "TideWe",
    "End Date": "NEVER",
    "Title": "20%OFF Clearance Sale",
    "Tracking URL": "https://www.shareasale.com/u.cfm?d=1111605&m=92895&u=233101",
    "Category": "Clearance item",
    "Description": "20%OFF Clearance Sale",
    "Coupon Code": "TWS20"
  },
  {
    "Merchant": "TideWe",
    "End Date": "NEVER",
    "Title": "30%OFF Clearance Sale",
    "Tracking URL": "https://www.shareasale.com/u.cfm?d=1271854&m=92895&u=233101",
    "Category": "Clearance item",
    "Description": "30%OFF Clearance Sale",
    "Coupon Code": "TWS30"
  },
  {
    "Merchant": "TideWe",
    "End Date": "NEVER",
    "Title": "UP TO 70% OFF MEGA SALE!",
    "Tracking URL": "https://www.shareasale.com/u.cfm?d=1271855&m=92895&u=233101",
    "Category": "Clearance item",
    "Description": "Buy 2 Get 2nd 70% off clearance items",
    "Coupon Code": "TWS70"
  },
  {
    "Merchant": "TideWe",
    "End Date": "NEVER",
    "Title": "BOGO Hunting Sale!",
    "Tracking URL": "https://www.shareasale.com/u.cfm?d=1269797&m=92895&u=233101",
    "Category": "deal",
    "Description": "Buy A Hunting Blind, Get A Heated Clothes Free!",
    "Coupon Code": "BOGO"
  },
  {
    "Merchant": "TideWe",
    "End Date": "NEVER",
    "Title": "15% OFF BOOTS SALE",
    "Tracking URL": "https://www.shareasale.com/u.cfm?d=1270343&m=92895&u=233101",
    "Category": "boots",
    "Description": "15% OFF BOOTS SALE",
    "Coupon Code": "AFF15"
  },
  {
    "Merchant": "TideWe",
    "End Date": "NEVER",
    "Title": "15% Off Backpacks + Free Shipping",
    "Tracking URL": "https://www.shareasale.com/u.cfm?d=1270339&m=92895&u=233101",
    "Category": "hunting backpacks",
    "Description": "15% Off Backpacks + Free Shipping",
    "Coupon Code": "AFF15"
  },
  {
    "Merchant": "TideWe",
    "End Date": "NEVER",
    "Title": "15% OFF NEW Arrival",
    "Tracking URL": "https://www.shareasale.com/u.cfm?d=1228810&m=92895&u=233101",
    "Category": "",
    "Description": "15% OFF NEW HUNTING GEAR",
    "Coupon Code": "AFF15"
  },
  {
    "Merchant": "TideWe",
    "End Date": "NEVER",
    "Title": "$50 OFF QuestWade Elite Hunting Waders",
    "Tracking URL": "https://www.shareasale.com/u.cfm?d=1237242&m=92895&u=233101",
    "Category": "new arrival",
    "Description": "$50 OFF QuestWade Elite Hunting Waders",
    "Coupon Code": "WDS50"
  },
  {
    "Merchant": "TideWe",
    "End Date": "NEVER",
    "Title": "$50 OFF QuestWade Elite Hunting Waders",
    "Tracking URL": "https://www.shareasale.com/u.cfm?d=1251578&m=92895&u=233101",
    "Category": "waders",
    "Description": "$50 OFF QuestWade Elite Hunting Waders",
    "Coupon Code": "WDS50"
  },
  {
    "Merchant": "TideWe",
    "End Date": "NEVER",
    "Title": "TIDEWE DEALS FOR AFFILIATES",
    "Tracking URL": "https://www.shareasale.com/u.cfm?d=1114523&m=92895&u=233101",
    "Category": "",
    "Description": "YEAR ROUND SALES",
    "Coupon Code": ""
  },
  {
    "Merchant": "TideWe",
    "End Date": "NEVER",
    "Title": "Valentine's Day Sale",
    "Tracking URL": "https://www.shareasale.com/u.cfm?d=1265536&m=92895&u=233101",
    "Category": "",
    "Description": "Buy 1, get the 2nd 30% off",
    "Coupon Code": "VA30"
  },
  {
    "Merchant": "TideWe",
    "End Date": "NEVER",
    "Title": "Save $55 for Spring Hunting Sale",
    "Tracking URL": "https://www.shareasale.com/u.cfm?d=1261349&m=92895&u=233101",
    "Category": "campaign",
    "Description": "Save $55 on orders over $269",
    "Coupon Code": "WS55"
  },
  {
    "Merchant": "TideWe",
    "End Date": "NEVER",
    "Title": "Save $25 for Spring Hunting Sale",
    "Tracking URL": "https://www.shareasale.com/u.cfm?d=1261348&m=92895&u=233101",
    "Category": "campaign",
    "Description": "Save $25 on orders over $169",
    "Coupon Code": "WS25"
  },
  {
    "Merchant": "TideWe",
    "End Date": "NEVER",
    "Title": "Save $10 for Spring Hunting Sale",
    "Tracking URL": "https://www.shareasale.com/u.cfm?d=1261346&m=92895&u=233101",
    "Category": "campaign",
    "Description": "Save $10 on orders over $110",
    "Coupon Code": "WS10"
  },
  {
    "Merchant": "TideWe",
    "End Date": "NEVER",
    "Title": "Turkey Hunting Season",
    "Tracking URL": "https://www.shareasale.com/u.cfm?d=1055205&m=92895&u=233101",
    "Category": "",
    "Description": "UP TO 50% OFF",
    "Coupon Code": "AFF15"
  },
  {
    "Merchant": "TideWe",
    "End Date": "NEVER",
    "Title": "Early Turkey Hunting Sale",
    "Tracking URL": "https://www.shareasale.com/u.cfm?d=1095235&m=92895&u=233101",
    "Category": "turkey season",
    "Description": "Extra 15% off deal with code",
    "Coupon Code": "AFF15"
  },
  {
    "Merchant": "TideWe",
    "End Date": "NEVER",
    "Title": "15% OFF Heated Clothing",
    "Tracking URL": "https://www.shareasale.com/u.cfm?d=1239263&m=92895&u=233101",
    "Category": "Heated",
    "Description": "15% OFF Heated Clothing: waders, vests, waders",
    "Coupon Code": "AFF15"
  },
  {
    "Merchant": "TideWe",
    "End Date": "NEVER",
    "Title": "TideWe Heated Hunting Vest",
    "Tracking URL": "https://www.shareasale.com/u.cfm?d=1244040&m=92895&u=233101",
    "Category": "Heated",
    "Description": "15% OFF Heated Hunting Vest",
    "Coupon Code": "AFF15"
  },
  {
    "Merchant": "TideWe",
    "End Date": "NEVER",
    "Title": "Clearance | 22% OFF Inferno Men's Heated Jacket",
    "Tracking URL": "https://www.shareasale.com/u.cfm?d=1258903&m=92895&u=233101",
    "Category": "hunting clothing",
    "Description": "Lowest price with extra 22% off discount",
    "Coupon Code": "HJ22"
  },
  {
    "Merchant": "TideWe",
    "End Date": "NEVER",
    "Title": "Buy 1, Get the 2nd 50% Off",
    "Tracking URL": "https://www.shareasale.com/u.cfm?d=1070189&m=92895&u=233101",
    "Category": "campaign",
    "Description": "Buy 1, get the 2nd 50% off",
    "Coupon Code": "NY50"
  },
  {
    "Merchant": "TideWe",
    "End Date": "NEVER",
    "Title": "10% OFF NEW ARRIVAL",
    "Tracking URL": "https://www.shareasale.com/u.cfm?d=1265122&m=92895&u=233101",
    "Category": "new arrival",
    "Description": "10% OFF NEW ARRIVAL",
    "Coupon Code": "NEW10"
  },
  {
    "Merchant": "TideWe",
    "End Date": "NEVER",
    "Title": "NEW YEAR SALE",
    "Tracking URL": "https://www.shareasale.com/u.cfm?d=1070188&m=92895&u=233101",
    "Category": "campaign",
    "Description": "No Threshold 10% OFF",
    "Coupon Code": "NY10"
  },
  {
    "Merchant": "TideWe",
    "End Date": "NEVER",
    "Title": "22% OFF Inferno Men's Heated Jacket",
    "Tracking URL": "https://www.shareasale.com/u.cfm?d=1258909&m=92895&u=233101",
    "Category": "Clearance item",
    "Description": "Heated Clothes Category",
    "Coupon Code": "HJ22"
  },
  {
    "Merchant": "TideWe",
    "End Date": "NEVER",
    "Title": "22% OFF Men's Soft Shell Heated Jacket",
    "Tracking URL": "https://www.shareasale.com/u.cfm?d=1263481&m=92895&u=233101",
    "Category": "Clearance item",
    "Description": "Overstock Deal Category",
    "Coupon Code": "HJ22"
  },
  {
    "Merchant": "TideWe",
    "End Date": "NEVER",
    "Title": "12% OFF Winter Heated Gear",
    "Tracking URL": "https://www.shareasale.com/u.cfm?d=1255444&m=92895&u=233101",
    "Category": "Heated",
    "Description": "12% OFF Heated Hunting Gear",
    "Coupon Code": "HT12"
  },
  {
    "Merchant": "TideWe",
    "End Date": "NEVER",
    "Title": "20% OFF Overstock Sale ",
    "Tracking URL": "https://www.shareasale.com/u.cfm?d=1258178&m=92895&u=233101",
    "Category": "Clearance item",
    "Description": "20% OFF Overstock Sale ",
    "Coupon Code": "OS20"
  },
  {
    "Merchant": "TideWe",
    "End Date": "NEVER",
    "Title": "18% OFF Overstock Sale ",
    "Tracking URL": "https://www.shareasale.com/u.cfm?d=1258177&m=92895&u=233101",
    "Category": "Clearance item",
    "Description": "18% OFF Overstock Sale ",
    "Coupon Code": "OS18"
  },
  {
    "Merchant": "TideWe",
    "End Date": "NEVER",
    "Title": "22% OFF Inferno Men's Heated Jacket",
    "Tracking URL": "https://www.shareasale.com/u.cfm?d=1258908&m=92895&u=233101",
    "Category": "Clearance item",
    "Description": "Hunting Clothes Category",
    "Coupon Code": "HJ22"
  },
  {
    "Merchant": "TideWe",
    "End Date": "NEVER",
    "Title": "22% OFF Inferno Men's Heated Jacket",
    "Tracking URL": "https://www.shareasale.com/u.cfm?d=1258906&m=92895&u=233101",
    "Category": "Clearance item",
    "Description": "Overstock Deal Category",
    "Coupon Code": "HJ22"
  },
  {
    "Merchant": "TideWe",
    "End Date": "NEVER",
    "Title": "22% OFF Inferno Men's Heated Jacket",
    "Tracking URL": "https://www.shareasale.com/u.cfm?d=1258904&m=92895&u=233101",
    "Category": "Clearance item",
    "Description": "Overstock Sale Category",
    "Coupon Code": "HJ22"
  },
  {
    "Merchant": "TideWe",
    "End Date": "NEVER",
    "Title": "NEW YEAR SALE",
    "Tracking URL": "https://www.shareasale.com/u.cfm?d=1261365&m=92895&u=233101",
    "Category": "",
    "Description": "20% OFF TWO PRODUCTS",
    "Coupon Code": "NEW20"
  },
  {
    "Merchant": "TideWe",
    "End Date": "NEVER",
    "Title": "NEW YEAR SALE",
    "Tracking URL": "https://www.shareasale.com/u.cfm?d=1261364&m=92895&u=233101",
    "Category": "",
    "Description": "16% OFF on orders $85",
    "Coupon Code": "NEW16"
  },
  {
    "Merchant": "TideWe",
    "End Date": "NEVER",
    "Title": "16% off Discount for TideWe Christmas Deals",
    "Tracking URL": "https://www.shareasale.com/u.cfm?d=1259101&m=92895&u=233101",
    "Category": "Sports",
    "Description": "16% off discount for orders over $79",
    "Coupon Code": "XMAS16"
  },
  {
    "Merchant": "TideWe",
    "End Date": "NEVER",
    "Title": "16% off Discount for TideWe Christmas Deals",
    "Tracking URL": "https://www.shareasale.com/u.cfm?d=735155&m=92895&u=233101",
    "Category": "Sports",
    "Description": "16% off discount for orders over $79",
    "Coupon Code": "XMAS18"
  },
  {
    "Merchant": "TideWe",
    "End Date": "NEVER",
    "Title": "20% off Discount for TideWe Christmas Deals",
    "Tracking URL": "https://www.shareasale.com/u.cfm?d=735154&m=92895&u=233101",
    "Category": "campaign",
    "Description": "20% off discount for orders over $159",
    "Coupon Code": "XMAS22"
  },
  {
    "Merchant": "TideWe",
    "End Date": "NEVER",
    "Title": "18% OFF Inferno Men's Heated Jacket",
    "Tracking URL": "https://www.shareasale.com/u.cfm?d=1063310&m=92895&u=233101",
    "Category": "hunting clothing",
    "Description": "18% OFF Inferno Men's Heated Jacket",
    "Coupon Code": "INF18"
  },
  {
    "Merchant": "TideWe",
    "End Date": "NEVER",
    "Title": "Save $100 on DeepWade Zip Duck Waders",
    "Tracking URL": "https://www.shareasale.com/u.cfm?d=1056232&m=92895&u=233101",
    "Category": "",
    "Description": "$100 discounts on waterfowl duck waders!",
    "Coupon Code": "WD100"
  },
  {
    "Merchant": "TideWe",
    "End Date": "NEVER",
    "Title": "Buy 1 Get 2nd 25% Off All",
    "Tracking URL": "https://www.shareasale.com/u.cfm?d=1100458&m=92895&u=233101",
    "Category": "deal",
    "Description": "Buy 1, Get 2nd item 25% Off",
    "Coupon Code": "NH25"
  },
  {
    "Merchant": "TideWe",
    "End Date": "NEVER",
    "Title": "Clearance All Sale",
    "Tracking URL": "https://www.shareasale.com/u.cfm?d=1114530&m=92895&u=233101",
    "Category": "Clearance item",
    "Description": "SAVE UP TO 50% OFF SEASON DEALS",
    "Coupon Code": "TWS50"
  },
  {
    "Merchant": "TideWe",
    "End Date": "NEVER",
    "Title": "Clearance All + Extra 5% Off Code",
    "Tracking URL": "https://www.shareasale.com/u.cfm?d=1101705&m=92895&u=233101",
    "Category": "",
    "Description": "Biggest Clearance Sale",
    "Coupon Code": "SAVE5"
  },
  {
    "Merchant": "TideWe",
    "End Date": "NEVER",
    "Title": "New Arrival Sale | $50 OFF QuestWade Wader",
    "Tracking URL": "https://www.shareasale.com/u.cfm?d=1232917&m=92895&u=233101",
    "Category": "waders",
    "Description": "$50 OFF QuestWade Wader",
    "Coupon Code": "WDS50 "
  },
  {
    "Merchant": "TideWe",
    "End Date": "NEVER",
    "Title": "15% off Hunting Clothing",
    "Tracking URL": "https://www.shareasale.com/u.cfm?d=1123766&m=92895&u=233101",
    "Category": "",
    "Description": "15% off Hunting Clothing",
    "Coupon Code": "HC15"
  },
  {
    "Merchant": "TideWe",
    "End Date": "NEVER",
    "Title": "SAVE 15% Off Collection",
    "Tracking URL": "https://www.shareasale.com/u.cfm?d=1100460&m=92895&u=233101",
    "Category": "deal",
    "Description": "SAVE 15% Off Products under this collection",
    "Coupon Code": "GEAR15"
  },
  {
    "Merchant": "TideWe",
    "End Date": "NEVER",
    "Title": "SAVE 15% OFF",
    "Tracking URL": "https://www.shareasale.com/u.cfm?d=1114525&m=92895&u=233101",
    "Category": "deal",
    "Description": "Extra 15% off deal with code; only for this link",
    "Coupon Code": "AFF15"
  }
]